vmware_fusion_py/__init__.py
vmware_fusion_py/vmware.py
vmware_fusion_py-1.0.0b1.dist-info/LICENSE
vmware_fusion_py-1.0.0b1.dist-info/METADATA
vmware_fusion_py-1.0.0b1.dist-info/WHEEL
vmware_fusion_py-1.0.0b1.dist-info/top_level.txt
vmware_fusion_py-1.0.0b1.dist-info/RECORD
