Metadata-Version: 2.1
Name: vmware-fusion-py
Version: 1.0.0b1
Summary: A Python library for interacting with the VMWare Fusion CLI
Author-email: Ahmet Mutlugun <ahmet.mutlugun@gmail.com>
Project-URL: homepage, https://github.com/ahmetmutlugun/vmware-fusion-py
Project-URL: repository, https://github.com/ahmetmutlugun/vmware-fusion-py
Keywords: vmware,fusion,interface,python,vmware fusion,MacOS,library,virtualization
License-File: LICENSE
